joyokanji/__init__.py
joyokanji/utility.py
joyokanji/config/kanji.json
joyokanji/config/variants.json
joyokanji-1.1.0.dist-info/licenses/LICENSE
joyokanji-1.1.0.dist-info/METADATA
joyokanji-1.1.0.dist-info/WHEEL
joyokanji-1.1.0.dist-info/top_level.txt
joyokanji-1.1.0.dist-info/RECORD
