Metadata-Version: 2.4
Name: joyokanji
Version: 1.1.0
Summary: The joyokanji converts old-form kanji characters into new-form kanji characters.
Author: new-village
License:                                  Apache License
Project-URL: Homepage, https://github.com/new-village/joyo-kanji
Project-URL: Issues, https://github.com/new-village/joyo-kanji/issues
Keywords: kanji,japanese,normalization,text
Classifier: Programming Language :: Python :: 3
Classifier: Programming Language :: Python :: 3 :: Only
Classifier: Programming Language :: Python :: 3.11
Classifier: Programming Language :: Python :: 3.12
Classifier: Programming Language :: Python :: 3.13
Classifier: License :: OSI Approved :: Apache Software License
Classifier: Operating System :: OS Independent
Classifier: Topic :: Text Processing :: Linguistic
Requires-Python: >=3.11
License-File: LICENSE
Provides-Extra: pdf
Requires-Dist: pdfminer.six; extra == "pdf"
Provides-Extra: ocr
Requires-Dist: pypdfium2; extra == "ocr"
Requires-Dist: pytesseract; extra == "ocr"
Provides-Extra: dev
Requires-Dist: pytest; extra == "dev"
Requires-Dist: build; extra == "dev"
Dynamic: license-file
